cores/__init__.py
cores/commands/delete_queue.py
cores/component/client.py
cores/component/firebase_service.py
cores/component/jwt.py
cores/component/mail_service.py
cores/component/memcache.py
cores/component/rabbitmq.py
cores/component/redis.py
cores/component/sqlalchemy.py
cores/component/mongodb/database.py
cores/component/mongodb/service_base.py
cores/component/mongodb/service_base_contract.py
cores/configs/api_configs.py
cores/depends/authorization.py
cores/enum/cache.py
cores/interface/index.py
cores/logger/logging.py
cores/logger/logging_setup.py
cores/middleware/auth.py
cores/middleware/index.py
cores/model/base_error.py
cores/model/base_model.py
cores/model/event.py
cores/model/paging.py
cores/model/profile.py
cores/repository/sqlalchemy_repository.py
cores/repository/rpc/auth_client.py
cores/repository/rpc/client_base.py
cores/repository/rpc/noti.py
cores/repository/rpc/notifier_client.py
cores/repository/rpc/profile.py
cores/repository/rpc/profile_client.py
cores/repository/rpc/resource_client.py
cores/repository/rpc/secret_key_menagement_client.py
cores/repository/rpc/service_management_client.py
cores/repository/rpc/sms_client.py
cores/repository/rpc/sso_client.py
cores/repository/rpc/streaming_client.py
cores/repository/rpc/telegram_client.py
cores/repository/rpc/user_client.py
cores/repository/rpc/verify_token_rpc.py
cores/repository/rpc/vnetwork_client.py
cores/repository/rpc/vote_client.py
cores/repository/rpc/workflow_client.py
cores/transport/http_service.py
cores/utils/index.py
cores/utils/reason_phrases.py
cores/utils/status_codes.py
cores/utils/token_manager.py
tt_erp_cores-0.2.0.dist-info/licenses/LICENSE
tt_erp_cores-0.2.0.dist-info/METADATA
tt_erp_cores-0.2.0.dist-info/WHEEL
tt_erp_cores-0.2.0.dist-info/top_level.txt
tt_erp_cores-0.2.0.dist-info/RECORD
