Metadata-Version: 2.4
Name: tt-erp-cores
Version: 0.2.0
Summary: Core utilities and base components for royalty backend
Author-email: Bùi Nguyễn Phú Đang <phudang@tuoitre.com.vn>
Requires-Python: >=3.8
License-File: LICENSE
Requires-Dist: fastapi>=0.95.0
Requires-Dist: sqlalchemy>=2.0.0
Requires-Dist: pydantic>=2.0.0
Requires-Dist: python-dotenv>=1.0.0
Requires-Dist: uvicorn>=0.22.0
Requires-Dist: pydantic[email]>=2.0.0
Dynamic: license-file
